dvcs/__init__.py
dvcs/__main__.py
dvcs/dvcs.py
dvcs-0.1.0.dist-info/METADATA
dvcs-0.1.0.dist-info/WHEEL
dvcs-0.1.0.dist-info/entry_points.txt
dvcs-0.1.0.dist-info/namespace_packages.txt
dvcs-0.1.0.dist-info/top_level.txt
dvcs-0.1.0.dist-info/RECORD
